asyncpg_wrapper/__init__.py
asyncpg_wrapper/apgwrap.py
asyncpg_wrapper-0.1.2.dist-info/METADATA
asyncpg_wrapper-0.1.2.dist-info/WHEEL
asyncpg_wrapper-0.1.2.dist-info/top_level.txt
asyncpg_wrapper-0.1.2.dist-info/RECORD
