Metadata-Version: 2.1
Name: asyncpg_wrapper
Version: 0.1.2
Summary: AsyncPG Easy-To-Use wrapper
Home-page: https://github.com/nissle59/asyncpg_wrapper
Author: Nissle
Author-email: nixncom@gmail.com
Classifier: Programming Language :: Python :: 3
Classifier: License :: OSI Approved :: MIT License
Classifier: Operating System :: OS Independent
Requires-Python: >=3.6
Requires-Dist: asyncpg >=0.29.0
